{
  "packages/amqp": "4.0.0",
  "packages/async": "4.0.0",
  "packages/aws": "4.0.0",
  "packages/core": "4.0.0",
  "packages/codmod": "3.0.0",
  "packages/elasticsearch": "4.0.0",
  "packages/gcp": "4.0.0",
  "packages/google-auth": "4.0.0",
  "packages/graphql": "4.0.0",
  "packages/hawk": "4.0.0",
  "packages/kubernetes": "4.0.0",
  "packages/mongodb": "4.0.0",
  "packages/postgres": "4.0.0",
  "packages/profiler": "4.0.0",
  "packages/profiler-aws-xray": "4.0.0",
  "packages/shell": "4.0.0",
  "packages/tsc-esm": "2.0.0",
  "packages/websockets": "4.0.0",
  "packages/workout": "4.0.0"
}
